revolve2/simulation/__init__.py
revolve2/simulation/py.typed
revolve2/simulation/scene/__init__.py
revolve2/simulation/scene/_aabb.py
revolve2/simulation/scene/_color.py
revolve2/simulation/scene/_control_interface.py
revolve2/simulation/scene/_joint.py
revolve2/simulation/scene/_joint_fixed.py
revolve2/simulation/scene/_joint_hinge.py
revolve2/simulation/scene/_multi_body_system.py
revolve2/simulation/scene/_pose.py
revolve2/simulation/scene/_rigid_body.py
revolve2/simulation/scene/_scene.py
revolve2/simulation/scene/_simulation_handler.py
revolve2/simulation/scene/_simulation_state.py
revolve2/simulation/scene/_uuid_key.py
revolve2/simulation/scene/conversion/__init__.py
revolve2/simulation/scene/conversion/_multi_body_system_to_urdf.py
revolve2/simulation/scene/geometry/__init__.py
revolve2/simulation/scene/geometry/_geometry.py
revolve2/simulation/scene/geometry/_geometry_box.py
revolve2/simulation/scene/geometry/_geometry_heightmap.py
revolve2/simulation/scene/geometry/_geometry_plane.py
revolve2/simulation/scene/geometry/_geometry_sphere.py
revolve2/simulation/scene/geometry/textures/__init__.py
revolve2/simulation/scene/geometry/textures/_map_type.py
revolve2/simulation/scene/geometry/textures/_texture.py
revolve2/simulation/scene/geometry/textures/_texture_reference.py
revolve2/simulation/scene/sensors/__init__.py
revolve2/simulation/scene/sensors/_camera_sensor.py
revolve2/simulation/scene/sensors/_imu_sensor.py
revolve2/simulation/scene/sensors/_sensor.py
revolve2/simulation/scene/vector2/__init__.py
revolve2/simulation/scene/vector2/vector2.py
revolve2/simulation/scene/vector2/vector2aux.py
revolve2/simulation/simulator/__init__.py
revolve2/simulation/simulator/_batch.py
revolve2/simulation/simulator/_batch_parameters.py
revolve2/simulation/simulator/_record_settings.py
revolve2/simulation/simulator/_simulator.py
revolve2/simulation/simulator/_viewer.py
revolve2_simulation-1.2.4.dist-info/METADATA
revolve2_simulation-1.2.4.dist-info/WHEEL
revolve2_simulation-1.2.4.dist-info/RECORD
